mcp_mesh_core/__init__.py
mcp_mesh_core/mcp_mesh_core.cpython-313-darwin.so
mcp_mesh_core-0.8.1.dist-info/METADATA
mcp_mesh_core-0.8.1.dist-info/WHEEL
mcp_mesh_core-0.8.1.dist-info/RECORD
