Metadata-Version: 2.4
Name: mcp-mesh-core
Version: 0.8.1
Classifier: Development Status :: 4 - Beta
Classifier: Intended Audience :: Developers
Classifier: License :: OSI Approved :: MIT License
Classifier: Programming Language :: Rust
Classifier: Programming Language :: Python :: 3
Classifier: Programming Language :: Python :: 3.11
Classifier: Programming Language :: Python :: 3.12
Classifier: Programming Language :: Python :: 3.13
Classifier: Programming Language :: Python :: 3.14
Classifier: Programming Language :: Python :: Implementation :: CPython
Classifier: Topic :: Software Development :: Libraries :: Python Modules
Classifier: Topic :: System :: Distributed Computing
Summary: Rust core runtime for MCP Mesh agents
Author-email: MCP Mesh Contributors <noreply@mcp-mesh.dev>
License: MIT
Requires-Python: >=3.11
Project-URL: Homepage, https://github.com/dhyansraj/mcp-mesh
Project-URL: Issues, https://github.com/dhyansraj/mcp-mesh/issues
Project-URL: Repository, https://github.com/dhyansraj/mcp-mesh
